setup.py
guessing_game_20250222/__init__.py
guessing_game_20250222/cli.py
guessing_game_20250222/guessing_game_functions.py
guessing_game_20250222.egg-info/PKG-INFO
guessing_game_20250222.egg-info/SOURCES.txt
guessing_game_20250222.egg-info/dependency_links.txt
guessing_game_20250222.egg-info/entry_points.txt
guessing_game_20250222.egg-info/not-zip-safe
guessing_game_20250222.egg-info/top_level.txt