Metadata-Version: 2.1
Name: guessing-game-20250222
Version: 1.0
Summary: A number guessing game in termal/cli
Author: fmcgh
Author-email: fmcgh@github.user
